[
  {
    "id": "2mdD8UMitc7BpIRYkpx3FDkClM8",
    "airline": "qantas",
    "flightNumber": "qa100",
    "origin": "DFW",
    "destination": "XNA",
    "departureTime": "10:00 AM",
    "arrivalTime": "12:00 PM",
    "duration": "2h 0m",
    "cabinClass": "economy",
    "points": "8000",
    "cash": 5.6,
    "seatsAvailable": 0,
    "realTimeData": true,
    "lastUpdated": "2025-04-21 15:54:34",
    "layovers": []
  },
  {
    "id": "2ng2m6y2Was7bnRRHbLszfubI0M",
    "airline": "American Airlines",
    "flightNumber": "Am101",
    "origin": "DFW",
    "destination": "XNA",
    "departureTime": "10:00 AM",
    "arrivalTime": "12:00 PM",
    "duration": "2h 0m",
    "cabinClass": "economy",
    "points": "8500",
    "cash": 5.6,
    "seatsAvailable": 0,
    "realTimeData": true,
    "lastUpdated": "2025-04-21 15:54:34",
    "layovers": []
  },
  {
    "id": "2mdglIJte3cRJv8k6RNbdPc7g9h",
    "airline": "Alaska Airlines",
    "flightNumber": "Al102",
    "origin": "DFW",
    "destination": "XNA",
    "departureTime": "10:00 AM",
    "arrivalTime": "12:00 PM",
    "duration": "2h 0m",
    "cabinClass": "economy",
    "points": "4500",
    "cash": 18.1,
    "seatsAvailable": 4,
    "realTimeData": true,
    "lastUpdated": "2025-04-21 15:54:34",
    "layovers": []
  },
  {
    "id": "2mq6P8uUqQEQ92kdbqrWfXVTGH6",
    "airline": "United Airlines",
    "flightNumber": "Un103",
    "origin": "DFW",
    "destination": "XNA",
    "departureTime": "10:00 AM",
    "arrivalTime": "12:00 PM",
    "duration": "2h 0m",
    "cabinClass": "economy",
    "points": "15000",
    "cash": 5.6,
    "seatsAvailable": 9,
    "realTimeData": true,
    "lastUpdated": "2025-04-21 15:54:34",
    "layovers": []
  }
]