[
  {
    "id": "2gnsFrmh6u0dgrwxkUTpLhiHD1v",
    "airline": "United Airlines",
    "flightNumber": "Un100",
    "origin": "SEA",
    "destination": "EWR",
    "departureTime": "10:00 AM",
    "arrivalTime": "12:00 PM",
    "duration": "2h 0m",
    "cabinClass": "economy",
    "points": "15000",
    "cash": 5.6,
    "seatsAvailable": 9,
    "realTimeData": true,
    "lastUpdated": "2025-04-16 13:43:43",
    "layovers": []
  },
  {
    "id": "2g4OvpEansUWvPbHnUhJxs5MMry",
    "airline": "qantas",
    "flightNumber": "qa101",
    "origin": "SEA",
    "destination": "EWR",
    "departureTime": "10:00 AM",
    "arrivalTime": "12:00 PM",
    "duration": "2h 0m",
    "cabinClass": "economy",
    "points": "20200",
    "cash": 5.6,
    "seatsAvailable": 0,
    "realTimeData": true,
    "lastUpdated": "2025-04-16 13:43:43",
    "layovers": []
  },
  {
    "id": "2hEjYcPCi2L1IFMw3vLvKBVEqmR",
    "airline": "American Airlines",
    "flightNumber": "Am102",
    "origin": "SEA",
    "destination": "EWR",
    "departureTime": "10:00 AM",
    "arrivalTime": "12:00 PM",
    "duration": "2h 0m",
    "cabinClass": "economy",
    "points": "14000",
    "cash": 5.6,
    "seatsAvailable": 3,
    "realTimeData": true,
    "lastUpdated": "2025-04-16 13:43:43",
    "layovers": []
  },
  {
    "id": "2gQTlx6xOdpTWcZeQMlOSkVKeba",
    "airline": "Alaska Airlines",
    "flightNumber": "Al103",
    "origin": "SEA",
    "destination": "EWR",
    "departureTime": "10:00 AM",
    "arrivalTime": "12:00 PM",
    "duration": "2h 0m",
    "cabinClass": "economy",
    "points": "22500",
    "cash": 18.1,
    "seatsAvailable": 9,
    "realTimeData": true,
    "lastUpdated": "2025-04-16 13:43:43",
    "layovers": []
  },
  {
    "id": "2v8MNf6ol0bAoZpLGVHqo70VDKu",
    "airline": "azul",
    "flightNumber": "az104",
    "origin": "SEA",
    "destination": "EWR",
    "departureTime": "10:00 AM",
    "arrivalTime": "12:00 PM",
    "duration": "2h 0m",
    "cabinClass": "economy",
    "points": "45500",
    "cash": 25.99,
    "seatsAvailable": 0,
    "realTimeData": true,
    "lastUpdated": "2025-04-16 13:43:43",
    "layovers": []
  },
  {
    "id": "2g4GnpkIJ1H54RUXbdZk17mDzDp",
    "airline": "Air Canada",
    "flightNumber": "Ai105",
    "origin": "SEA",
    "destination": "EWR",
    "departureTime": "10:00 AM",
    "arrivalTime": "12:00 PM",
    "duration": "2h 0m",
    "cabinClass": "economy",
    "points": "15000",
    "cash": 54.79,
    "seatsAvailable": 0,
    "realTimeData": true,
    "lastUpdated": "2025-04-16 13:43:43",
    "layovers": []
  },
  {
    "id": "2ft0lzN6kJiNrxtQAvN1NfTULWT",
    "airline": "velocity",
    "flightNumber": "ve106",
    "origin": "SEA",
    "destination": "EWR",
    "departureTime": "10:00 AM",
    "arrivalTime": "12:00 PM",
    "duration": "2h 0m",
    "cabinClass": "economy",
    "points": "23500",
    "cash": 23.3,
    "seatsAvailable": 9,
    "realTimeData": true,
    "lastUpdated": "2025-04-16 13:43:43",
    "layovers": []
  }
]